rsi_dstools/__init__.py
rsi_dstools/utils.py
rsi_dstools/apiutil/Dockerfile
rsi_dstools/apiutil/__init__.py
rsi_dstools/apiutil/api.py
rsi_dstools/apiutil/docker-compose.yml
rsi_dstools/apiutil/python_schemas.py
rsi_dstools/apiutil/requirements.txt
rsi_dstools/azureutils/README.md
rsi_dstools/azureutils/__init__.py
rsi_dstools/azureutils/azure_test_auth.py
rsi_dstools/azureutils/azureconfig.py
rsi_dstools/azureutils/azurerun.py
rsi_dstools/azureutils/setup_run_template.py
rsi_dstools/azureutils/example_run/azure-config.json:Zone.Identifier
rsi_dstools/azureutils/example_run/azure-mlstudio-app-auth-config.json:Zone.Identifier
rsi_dstools/azureutils/example_run/azure-rasabot-app-auth-config.json:Zone.Identifier
rsi_dstools/azureutils/example_run/debug_endpoint.ipynb
rsi_dstools/azureutils/example_run/forms-sql-config.json:Zone.Identifier
rsi_dstools/azureutils/example_run/local-test-RunScript-.ipynb
rsi_dstools/azureutils/example_run/local-test-model-scoring.ipynb
rsi_dstools/azureutils/example_run/score.py
rsi_dstools/azureutils/example_run/test-AzureRun-submit.ipynb
rsi_dstools/azureutils/example_run/test-deploy-azure-model.ipynb
rsi_dstools/azureutils/example_run/test_dependencies_checks.ipynb
rsi_dstools/azureutils/example_run/test_local_deploy.ipynb
rsi_dstools/azureutils/example_run/test_whl_pkg_in_env.ipynb
rsi_dstools/azureutils/example_run/train-in-azure.yml
rsi_dstools/azureutils/example_run/train.py
rsi_dstools/azureutils/example_run/api_ml_model_cache/sklearn-ridge-regr-diabetes_/MLmodel
rsi_dstools/azureutils/example_run/api_ml_model_cache/sklearn-ridge-regr-diabetes_/conda.yaml
rsi_dstools/azureutils/example_run/api_ml_model_cache/sklearn-ridge-regr-diabetes_/model.pkl
rsi_dstools/azureutils/example_run/api_ml_model_cache/sklearn-ridge-regr-diabetes_/python_env.yaml
rsi_dstools/azureutils/example_run/api_ml_model_cache/sklearn-ridge-regr-diabetes_/requirements.txt
rsi_dstools/azureutils/example_run/example_imports/___init__.py
rsi_dstools-0.0.2.dist-info/METADATA
rsi_dstools-0.0.2.dist-info/WHEEL
rsi_dstools-0.0.2.dist-info/licenses/LICENSE
rsi_dstools-0.0.2.dist-info/RECORD
